<?xml version="1.0" encoding="UTF-8"?>
<!DOCTYPE pkgmetadata SYSTEM "https://www.gentoo.org/dtd/metadata.dtd">
<pkgmetadata>
	<maintainer type="person">
		<email>mathieu.tortuyaux@gmail.com</email>
		<name>Mathieu Tortuyaux</name>
	</maintainer>
	<maintainer type="person">
		<email>dev@dyama.net</email>
		<name>Daichi Yamamoto</name>
	</maintainer>
	<longdescription lang="en">
	The goal of this project is to implement a simple system information tool in POSIX sh using features built into the language itself (where possible).
	The source code is highly documented and I hope it will act as a learning resource for POSIX sh and simple information detection across various different operating systems.
	</longdescription>
	<upstream>
		<bugs-to>https://github.com/dylanaraps/pfetch/issues</bugs-to>
		<remote-id type="github">dylanaraps/pfetch</remote-id>
	</upstream>
</pkgmetadata>

